openaiisrich/__init__.py
openaiisrich/openai-pricing.json
openaiisrich-0.6.0.dist-info/METADATA
openaiisrich-0.6.0.dist-info/WHEEL
openaiisrich-0.6.0.dist-info/top_level.txt
openaiisrich-0.6.0.dist-info/RECORD
