Metadata-Version: 2.1
Name: openaiisrich
Version: 0.6.0
Summary: latest pricing information of openai models, crowd maintained
Author-email: Martin Monperrus <martin.monperrus@gnieh.org>
